{
  "jobs": {
    "Job1": {
      "due_date": 1187,
      "operations": [
        {"machine": 3, "time": 76, "next": 2},
        {"machine": 12, "time": 17, "next": 3},
        {"machine": 1, "time": 58, "next": 4},
        {"machine": 14, "time": 26, "next": 5},
        {"machine": 2, "time": 90, "next": 6},
        {"machine": 9, "time": 77, "next": 7},
        {"machine": 10, "time": 63, "next": 8},
        {"machine": 7, "time": 87, "next": 9},
        {"machine": 5, "time": 74, "next": 10},
        {"machine": 8, "time": 35, "next": 11},
        {"machine": 13, "time": 60, "next": 12},
        {"machine": 4, "time": 90, "next": 13},
        {"machine": 15, "time": 64, "next": 14},
        {"machine": 6, "time": 68, "next": 15},
        {"machine": 11, "time": 28, "next": null}
      ]
    },
    "Job2": {
      "due_date": 1122,
      "operations": [
        {"machine": 6, "time": 5, "next": 2},
        {"machine": 9, "time": 79, "next": 3},
        {"machine": 10, "time": 71, "next": 4},
        {"machine": 4, "time": 42, "next": 5},
        {"machine": 2, "time": 71, "next": 6},
        {"machine": 14, "time": 20, "next": 7},
        {"machine": 12, "time": 86, "next": 8},
        {"machine": 1, "time": 88, "next": 9},
        {"machine": 15, "time": 47, "next": 10},
        {"machine": 8, "time": 62, "next": 11},
        {"machine": 5, "time": 37, "next": 12},
        {"machine": 13, "time": 87, "next": 13},
        {"machine": 11, "time": 47, "next": 14},
        {"machine": 7, "time": 97, "next": 15},
        {"machine": 3, "time": 24, "next": null}
      ]
    },
    "Job3": {
      "due_date": 1005,
      "operations": [
        {"machine": 6, "time": 2, "next": 2},
        {"machine": 3, "time": 67, "next": 3},
        {"machine": 9, "time": 28, "next": 4},
        {"machine": 15, "time": 98, "next": 5},
        {"machine": 14, "time": 66, "next": 6},
        {"machine": 2, "time": 42, "next": 7},
        {"machine": 7, "time": 46, "next": 8},
        {"machine": 10, "time": 23, "next": 9},
        {"machine": 13, "time": 94, "next": 10},
        {"machine": 5, "time": 25, "next": 11},
        {"machine": 12, "time": 89, "next": 12},
        {"machine": 1, "time": 3, "next": 13},
        {"machine": 8, "time": 38, "next": 14},
        {"machine": 4, "time": 76, "next": 15},
        {"machine": 11, "time": 76, "next": null}
      ]
    },
    "Job4": {
      "due_date": 714,
      "operations": [
        {"machine": 9, "time": 96, "next": 2},
        {"machine": 11, "time": 79, "next": 3},
        {"machine": 5, "time": 19, "next": 4},
        {"machine": 1, "time": 36, "next": 5},
        {"machine": 4, "time": 87, "next": 6},
        {"machine": 12, "time": 6, "next": 7},
        {"machine": 14, "time": 9, "next": 8},
        {"machine": 7, "time": 18, "next": 9},
        {"machine": 2, "time": 32, "next": 10},
        {"machine": 6, "time": 37, "next": 11},
        {"machine": 3, "time": 55, "next": 12},
        {"machine": 10, "time": 3, "next": 13},
        {"machine": 13, "time": 15, "next": 14},
        {"machine": 15, "time": 12, "next": 15},
        {"machine": 8, "time": 45, "next": null}
      ]
    },
    "Job5": {
      "due_date": 1019,
      "operations": [
        {"machine": 9, "time": 71, "next": 2},
        {"machine": 12, "time": 73, "next": 3},
        {"machine": 2, "time": 17, "next": 4},
        {"machine": 1, "time": 41, "next": 5},
        {"machine": 6, "time": 71, "next": 6},
        {"machine": 14, "time": 88, "next": 7},
        {"machine": 3, "time": 43, "next": 8},
        {"machine": 15, "time": 59, "next": 9},
        {"machine": 11, "time": 37, "next": 10},
        {"machine": 13, "time": 22, "next": 11},
        {"machine": 10, "time": 21, "next": 12},
        {"machine": 4, "time": 77, "next": 13},
        {"machine": 5, "time": 66, "next": 14},
        {"machine": 7, "time": 46, "next": 15},
        {"machine": 8, "time": 52, "next": null}
      ]
    },
    "Job6": {
      "due_date": 722,
      "operations": [
        {"machine": 12, "time": 19, "next": 2},
        {"machine": 4, "time": 12, "next": 3},
        {"machine": 14, "time": 87, "next": 4},
        {"machine": 10, "time": 22, "next": 5},
        {"machine": 15, "time": 41, "next": 6},
        {"machine": 2, "time": 29, "next": 7},
        {"machine": 1, "time": 6, "next": 8},
        {"machine": 8, "time": 4, "next": 9},
        {"machine": 5, "time": 79, "next": 10},
        {"machine": 6, "time": 78, "next": 11},
        {"machine": 11, "time": 21, "next": 12},
        {"machine": 13, "time": 27, "next": 13},
        {"machine": 7, "time": 16, "next": 14},
        {"machine": 3, "time": 54, "next": 15},
        {"machine": 9, "time": 60, "next": null}
      ]
    },
    "Job7": {
      "due_date": 1044,
      "operations": [
        {"machine": 14, "time": 96, "next": 2},
        {"machine": 4, "time": 39, "next": 3},
        {"machine": 12, "time": 82, "next": 4},
        {"machine": 11, "time": 15, "next": 5},
        {"machine": 6, "time": 22, "next": 6},
        {"machine": 13, "time": 29, "next": 7},
        {"machine": 1, "time": 64, "next": 8},
        {"machine": 5, "time": 92, "next": 9},
        {"machine": 15, "time": 68, "next": 10},
        {"machine": 7, "time": 60, "next": 11},
        {"machine": 8, "time": 37, "next": 12},
        {"machine": 9, "time": 10, "next": 13},
        {"machine": 10, "time": 47, "next": 14},
        {"machine": 3, "time": 68, "next": 15},
        {"machine": 2, "time": 74, "next": null}
      ]
    },
    "Job8": {
      "due_date": 992,
      "operations": [
        {"machine": 6, "time": 28, "next": 2},
        {"machine": 9, "time": 3, "next": 3},
        {"machine": 7, "time": 71, "next": 4},
        {"machine": 8, "time": 59, "next": 5},
        {"machine": 3, "time": 94, "next": 6},
        {"machine": 4, "time": 60, "next": 7},
        {"machine": 11, "time": 98, "next": 8},
        {"machine": 5, "time": 77, "next": 9},
        {"machine": 2, "time": 9, "next": 10},
        {"machine": 15, "time": 57, "next": 11},
        {"machine": 12, "time": 21, "next": 12},
        {"machine": 10, "time": 74, "next": 13},
        {"machine": 14, "time": 19, "next": 14},
        {"machine": 1, "time": 74, "next": 15},
        {"machine": 13, "time": 19, "next": null}
      ]
    },
    "Job9": {
      "due_date": 975,
      "operations": [
        {"machine": 13, "time": 7, "next": 2},
        {"machine": 9, "time": 38, "next": 3},
        {"machine": 10, "time": 63, "next": 4},
        {"machine": 8, "time": 69, "next": 5},
        {"machine": 4, "time": 13, "next": 6},
        {"machine": 7, "time": 56, "next": 7},
        {"machine": 12, "time": 53, "next": 8},
        {"machine": 14, "time": 58, "next": 9},
        {"machine": 11, "time": 2, "next": 10},
        {"machine": 1, "time": 93, "next": 11},
        {"machine": 3, "time": 90, "next": 12},
        {"machine": 6, "time": 6, "next": 13},
        {"machine": 2, "time": 66, "next": 14},
        {"machine": 5, "time": 76, "next": 15},
        {"machine": 15, "time": 60, "next": null}
      ]
    },
    "Job10": {
      "due_date": 1054,
      "operations": [
        {"machine": 6, "time": 85, "next": 2},
        {"machine": 15, "time": 46, "next": 3},
        {"machine": 12, "time": 75, "next": 4},
        {"machine": 5, "time": 34, "next": 5},
        {"machine": 11, "time": 33, "next": 6},
        {"machine": 9, "time": 94, "next": 7},
        {"machine": 10, "time": 50, "next": 8},
        {"machine": 3, "time": 20, "next": 9},
        {"machine": 14, "time": 4, "next": 10},
        {"machine": 13, "time": 28, "next": 11},
        {"machine": 8, "time": 60, "next": 12},
        {"machine": 2, "time": 74, "next": 13},
        {"machine": 1, "time": 90, "next": 14},
        {"machine": 4, "time": 51, "next": 15},
        {"machine": 7, "time": 67, "next": null}
      ]
    },
    "Job11": {
      "due_date": 936,
      "operations": [
        {"machine": 11, "time": 88, "next": 2},
        {"machine": 10, "time": 11, "next": 3},
        {"machine": 2, "time": 35, "next": 4},
        {"machine": 13, "time": 87, "next": 5},
        {"machine": 3, "time": 14, "next": 6},
        {"machine": 8, "time": 85, "next": 7},
        {"machine": 4, "time": 12, "next": 8},
        {"machine": 5, "time": 21, "next": 9},
        {"machine": 1, "time": 23, "next": 10},
        {"machine": 6, "time": 37, "next": 11},
        {"machine": 7, "time": 12, "next": 12},
        {"machine": 9, "time": 88, "next": 13},
        {"machine": 14, "time": 98, "next": 14},
        {"machine": 15, "time": 33, "next": 15},
        {"machine": 12, "time": 76, "next": null}
      ]
    },
    "Job12": {
      "due_date": 1078,
      "operations": [
        {"machine": 10, "time": 30, "next": 2},
        {"machine": 8, "time": 89, "next": 3},
        {"machine": 6, "time": 91, "next": 4},
        {"machine": 7, "time": 3, "next": 5},
        {"machine": 1, "time": 97, "next": 6},
        {"machine": 15, "time": 71, "next": 7},
        {"machine": 2, "time": 73, "next": 8},
        {"machine": 4, "time": 16, "next": 9},
        {"machine": 9, "time": 15, "next": 10},
        {"machine": 12, "time": 98, "next": 11},
        {"machine": 3, "time": 71, "next": 12},
        {"machine": 13, "time": 19, "next": 13},
        {"machine": 11, "time": 65, "next": 14},
        {"machine": 14, "time": 89, "next": 15},
        {"machine": 5, "time": 2, "next": null}
      ]
    },
    "Job13": {
      "due_date": 1208,
      "operations": [
        {"machine": 3, "time": 61, "next": 2},
        {"machine": 14, "time": 86, "next": 3},
        {"machine": 13, "time": 71, "next": 4},
        {"machine": 4, "time": 76, "next": 5},
        {"machine": 10, "time": 88, "next": 6},
        {"machine": 2, "time": 32, "next": 7},
        {"machine": 6, "time": 31, "next": 8},
        {"machine": 11, "time": 50, "next": 9},
        {"machine": 12, "time": 25, "next": 10},
        {"machine": 7, "time": 84, "next": 11},
        {"machine": 1, "time": 79, "next": 12},
        {"machine": 8, "time": 34, "next": 13},
        {"machine": 9, "time": 59, "next": 14},
        {"machine": 15, "time": 75, "next": 15},
        {"machine": 5, "time": 78, "next": null}
      ]
    },
    "Job14": {
      "due_date": 1040,
      "operations": [
        {"machine": 4, "time": 9, "next": 2},
        {"machine": 1, "time": 59, "next": 3},
        {"machine": 10, "time": 93, "next": 4},
        {"machine": 14, "time": 69, "next": 5},
        {"machine": 9, "time": 38, "next": 6},
        {"machine": 3, "time": 65, "next": 7},
        {"machine": 7, "time": 96, "next": 8},
        {"machine": 2, "time": 67, "next": 9},
        {"machine": 11, "time": 74, "next": 10},
        {"machine": 13, "time": 41, "next": 11},
        {"machine": 8, "time": 61, "next": 12},
        {"machine": 15, "time": 68, "next": 13},
        {"machine": 5, "time": 11, "next": 14},
        {"machine": 6, "time": 24, "next": 15},
        {"machine": 12, "time": 25, "next": null}
      ]
    },
    "Job15": {
      "due_date": 1128,
      "operations": [
        {"machine": 7, "time": 86, "next": 2},
        {"machine": 6, "time": 77, "next": 3},
        {"machine": 1, "time": 21, "next": 4},
        {"machine": 14, "time": 50, "next": 5},
        {"machine": 9, "time": 72, "next": 6},
        {"machine": 15, "time": 68, "next": 7},
        {"machine": 3, "time": 91, "next": 8},
        {"machine": 8, "time": 72, "next": 9},
        {"machine": 13, "time": 65, "next": 10},
        {"machine": 5, "time": 52, "next": 11},
        {"machine": 11, "time": 45, "next": 12},
        {"machine": 4, "time": 5, "next": 13},
        {"machine": 2, "time": 71, "next": 14},
        {"machine": 10, "time": 68, "next": 15},
        {"machine": 12, "time": 25, "next": null}
      ]
    },
    "Job16": {
      "due_date": 719,
      "operations": [
        {"machine": 7, "time": 37, "next": 2},
        {"machine": 9, "time": 27, "next": 3},
        {"machine": 1, "time": 23, "next": 4},
        {"machine": 8, "time": 26, "next": 5},
        {"machine": 5, "time": 2, "next": 6},
        {"machine": 2, "time": 36, "next": 7},
        {"machine": 12, "time": 20, "next": 8},
        {"machine": 11, "time": 65, "next": 9},
        {"machine": 14, "time": 61, "next": 10},
        {"machine": 15, "time": 27, "next": 11},
        {"machine": 13, "time": 35, "next": 12},
        {"machine": 3, "time": 50, "next": 13},
        {"machine": 10, "time": 45, "next": 14},
        {"machine": 4, "time": 80, "next": 15},
        {"machine": 6, "time": 19, "next": null}
      ]
    },
    "Job17": {
      "due_date": 1031,
      "operations": [
        {"machine": 14, "time": 5, "next": 2},
        {"machine": 3, "time": 57, "next": 3},
        {"machine": 2, "time": 70, "next": 4},
        {"machine": 9, "time": 95, "next": 5},
        {"machine": 4, "time": 46, "next": 6},
        {"machine": 13, "time": 36, "next": 7},
        {"machine": 7, "time": 88, "next": 8},
        {"machine": 15, "time": 42, "next": 9},
        {"machine": 12, "time": 49, "next": 10},
        {"machine": 10, "time": 23, "next": 11},
        {"machine": 6, "time": 63, "next": 12},
        {"machine": 8, "time": 77, "next": 13},
        {"machine": 5, "time": 47, "next": 14},
        {"machine": 11, "time": 88, "next": 15},
        {"machine": 1, "time": 7, "next": null}
      ]
    },
    "Job18": {
      "due_date": 1052,
      "operations": [
        {"machine": 14, "time": 29, "next": 2},
        {"machine": 8, "time": 64, "next": 3},
        {"machine": 6, "time": 23, "next": 4},
        {"machine": 12, "time": 42, "next": 5},
        {"machine": 5, "time": 33, "next": 6},
        {"machine": 7, "time": 65, "next": 7},
        {"machine": 11, "time": 92, "next": 8},
        {"machine": 15, "time": 80, "next": 9},
        {"machine": 3, "time": 49, "next": 10},
        {"machine": 10, "time": 3, "next": 11},
        {"machine": 1, "time": 83, "next": 12},
        {"machine": 4, "time": 20, "next": 13},
        {"machine": 9, "time": 63, "next": 14},
        {"machine": 13, "time": 78, "next": 15},
        {"machine": 2, "time": 85, "next": null}
      ]
    },
    "Job19": {
      "due_date": 1212,
      "operations": [
        {"machine": 10, "time": 67, "next": 2},
        {"machine": 3, "time": 47, "next": 3},
        {"machine": 11, "time": 48, "next": 4},
        {"machine": 12, "time": 57, "next": 5},
        {"machine": 8, "time": 84, "next": 6},
        {"machine": 2, "time": 63, "next": 7},
        {"machine": 15, "time": 48, "next": 8},
        {"machine": 4, "time": 70, "next": 9},
        {"machine": 7, "time": 85, "next": 10},
        {"machine": 9, "time": 93, "next": 11},
        {"machine": 6, "time": 1, "next": 12},
        {"machine": 5, "time": 63, "next": 13},
        {"machine": 13, "time": 87, "next": 14},
        {"machine": 1, "time": 29, "next": 15},
        {"machine": 14, "time": 90, "next": null}
      ]
    },
    "Job20": {
      "due_date": 966,
      "operations": [
        {"machine": 14, "time": 80, "next": 2},
        {"machine": 5, "time": 14, "next": 3},
        {"machine": 12, "time": 41, "next": 4},
        {"machine": 13, "time": 73, "next": 5},
        {"machine": 8, "time": 22, "next": 6},
        {"machine": 1, "time": 93, "next": 7},
        {"machine": 6, "time": 6, "next": 8},
        {"machine": 2, "time": 81, "next": 9},
        {"machine": 9, "time": 19, "next": 10},
        {"machine": 15, "time": 62, "next": 11},
        {"machine": 10, "time": 62, "next": 12},
        {"machine": 3, "time": 85, "next": 13},
        {"machine": 4, "time": 25, "next": 14},
        {"machine": 11, "time": 70, "next": 15},
        {"machine": 7, "time": 10, "next": null}
      ]
    }
  },
  "machines": [1, 2, 3, 4, 5, 6, 7, 8, 9, 10, 11, 12, 13, 14, 15]
}
